Metadata-Version: 2.1
Name: pranyaoptimalpricingmodel
Version: 0.0.1
Summary: An optimal pricing model that can be used for any new product launched in the market.
Home-page: 
Author: Pranya Chandratre
Author-email: pranya.chandratre002@nmims.edu.in
License: MIT
Keywords: optimal pricing model
Classifier: Development Status :: 5 - Production/Stable
Classifier: Intended Audience :: Education
Classifier: Operating System :: Microsoft :: Windows :: Windows 10
Classifier: License :: OSI Approved :: MIT License
Classifier: Programming Language :: Python :: 3
License-File: LICENCE.txt
